aura_boy/__init__.py
aura_boy/__main__.py
aura_boy/boy_grid.py
aura_boy/render.py
aura_boy/resize_grid.py
aura_boy/run.py
aura_boy-0.1.1.dist-info/METADATA
aura_boy-0.1.1.dist-info/WHEEL
aura_boy-0.1.1.dist-info/entry_points.txt
aura_boy-0.1.1.dist-info/top_level.txt
aura_boy-0.1.1.dist-info/RECORD
