Metadata-Version: 2.4
Name: aura-boy
Version: 0.1.1
Summary: Render the Aura Boat Boy in your terminal
Author-email: Yogesh Kumar <fbyogesh111@gmail.com>
License: MIT
Requires-Python: >=3.7
Requires-Dist: colorama
Requires-Dist: pillow
